LICENSE
MANIFEST.in
README.md
setup.cfg
setup.py
bin/balancer_test
factorio_balancers/__init__.py
factorio_balancers/balancer.py
factorio_balancers/entity_data.json
factorio_balancers/entity_mixins.py
factorio_balancers/exceptions.py
factorio_balancers/graph.py
factorio_balancers/utils.py
factorio_balancers.egg-info/PKG-INFO
factorio_balancers.egg-info/SOURCES.txt
factorio_balancers.egg-info/dependency_links.txt
factorio_balancers.egg-info/not-zip-safe
factorio_balancers.egg-info/requires.txt
factorio_balancers.egg-info/top_level.txt