Metadata-Version: 2.1
Name: factorio-balancers
Version: 0.2.4
Summary: A property testing simulator for balancers from the game Factorio
Home-page: https://github.com/tzwaan/factorio_balancers
Author: Tijmen Zwaan
Author-email: tijmen.zwaan@gmail.com
License: MIT
Download-URL: https://github.com/tzwaan/factorio_balancers/archive/v0.2.4.tar.gz
Keywords: factorio,balancer,blueprint
Platform: UNKNOWN
Classifier: Development Status :: 3 - Alpha
Classifier: Intended Audience :: Developers
Classifier: Intended Audience :: End Users/Desktop
Classifier: Programming Language :: Python :: 3
Classifier: License :: OSI Approved :: MIT License
Classifier: Operating System :: OS Independent
Classifier: Natural Language :: English
